linux_isolate_process/__init__.py
linux_isolate_process/isolate.py
linux_isolate_process-0.1.3.dist-info/LICENSE
linux_isolate_process-0.1.3.dist-info/METADATA
linux_isolate_process-0.1.3.dist-info/WHEEL
linux_isolate_process-0.1.3.dist-info/top_level.txt
linux_isolate_process-0.1.3.dist-info/RECORD
