Metadata-Version: 2.1
Name: linux_isolate_process
Version: 0.1.3
Summary: A package to isolate linux processes
Author-email: Aditya Pande <adityapande@google.com>
Project-URL: Homepage, https://github.com/adityapande-1995/linux_isolate_process
Requires-Python: >=3.8
License-File: LICENSE
